{
  "build": {
    "core": "megatinycore",
    "extra_flags": "-DARDUINO_attinyxy6 -DMILLIS_USE_TIMERD0 -DUARTBAUD5V",
    "f_cpu": "16000000L",
    "mcu": "attiny826",
    "variant": "txy6"
  },
  "hardware": {
    "oscillator": "internal"
  },
  "frameworks": [
    "arduino"
  ],
  "name": "ATtiny826",
  "upload": {
    "maximum_ram_size": 1024,
    "maximum_size": 8192,
    "protocol": "jtag2updi",
    "speed": 115200
  },
  "url": "https://www.microchip.com/wwwproducts/en/ATTINY826",
  "vendor": "Microchip"
}
